<?xml version="1.0" encoding="utf-8"?>
<publishData>
  <publishProfile publishUrl="ftp://lpeperfilempreendedor.com.br/LPE" deleteExistingFiles="False" ftpAnonymousLogin="False" ftpPassiveMode="True" msdeploySite="" msdeploySiteID="" msdeployRemoteSitePhysicalPath="" msdeployAllowUntrustedCertificate="False" msdeploySkipExtraFilesOnServer="True" msdeployMarkAsApp="False" profileName="Profile1" publishMethod="FTP" replaceMatchingFiles="True" userName="lpeperfi" savePWD="False" userPWD="" SelectedForPublish="True">
    <file relUrl="bin/NHibernate.dll" publishTime="03/14/2012 20:43:18" />
    <file relUrl="Views/EscolaridadeManager/Index.cshtml" publishTime="06/04/2013 12:13:14" />
    <file relUrl="Content/Scripts/OAT/pivot.js" publishTime="04/27/2013 00:40:52" />
    <file relUrl="Views/Home/OptionMenu.cshtml" publishTime="07/03/2013 13:21:28" />
    <file relUrl="Content/Scripts/jquery.jqGrid.min.js" publishTime="03/25/2013 09:53:44" />
    <file relUrl="Content/Scripts/jquery.validate.messages_ptbr.js" publishTime="03/25/2013 09:53:44" />
    <file relUrl="Content/css/smoothness/images/ui-bg_inset-soft_65_ffffff_1x100.png" publishTime="03/25/2013 09:53:44" />
    <file relUrl="Content/Scripts/jquery-ui-1.8.13.custom.min.js" publishTime="03/25/2013 09:53:44" />
    <file relUrl="Content/Scripts/jquery.tooltip.js" publishTime="03/25/2013 09:53:44" />
    <file relUrl="Views/Shared/_Layout.cshtml" publishTime="04/27/2013 00:40:51" />
    <file relUrl="Content/Scripts/jquery.validate.min.js" publishTime="03/25/2013 09:53:44" />
    <file relUrl="Content/Scripts/OAT/ghostdrag.js" publishTime="03/25/2013 09:53:44" />
    <file relUrl="Content/Scripts/jquery.maskMoney.0.2.js" publishTime="03/25/2013 09:53:44" />
    <file relUrl="Content/Scripts/Index.js" publishTime="05/02/2013 22:21:49" />
    <file relUrl="Web.config" publishTime="08/13/2013 15:22:20" />
    <file relUrl="Content/Scripts/jquery.maskedinput-1.3.min.js" publishTime="03/25/2013 09:53:44" />
    <file relUrl="Content/imgs/bar_top_index.png" publishTime="06/20/2013 12:34:24" />
    <file relUrl="bin/Modelo.pdb" publishTime="08/12/2013 18:38:08" />
    <file relUrl="bin/Iesi.Collections.xml" publishTime="03/14/2012 20:43:20" />
    <file relUrl="Content/Scripts/OAT/dimdown.png" publishTime="03/25/2013 09:53:44" />
    <file relUrl="Content/imgs/x_32x32.png" publishTime="03/20/2012 20:15:22" />
    <file relUrl="bin/Ninject.xml" publishTime="04/09/2013 11:57:32" />
    <file relUrl="Content/Scripts/OAT/Thread.js" publishTime="03/25/2013 09:53:44" />
    <file relUrl="bin/Ninject.Web.Mvc.pdb" publishTime="04/09/2013 11:57:32" />
    <file relUrl="bin/Ninject.Web.Mvc.xml" publishTime="04/09/2013 11:57:32" />
    <file relUrl="Global.asax" publishTime="03/14/2012 20:42:52" />
    <file relUrl="bin/FabricaNhibernate.dll" publishTime="08/28/2013 16:36:26" />
    <file relUrl="Content/Scripts/jquery.treeview.js" publishTime="03/25/2013 09:53:44" />
    <file relUrl="Views/NivelEscolaridadeManager/CreateAndUpdate.cshtml" publishTime="06/04/2013 10:51:53" />
    <file relUrl="Content/imgs/logo.png" publishTime="04/18/2013 22:20:53" />
    <file relUrl="Views/Usuario/Index.cshtml" publishTime="08/02/2012 18:49:46" />
    <file relUrl="Content/Scripts/OAT/pivot.css" publishTime="04/27/2013 00:40:52" />
    <file relUrl="bin/Ninject.Web.Mvc.dll" publishTime="04/09/2013 11:57:32" />
    <file relUrl="bin/Ninject.pdb" publishTime="04/09/2013 11:57:32" />
    <file relUrl="Content/Scripts/OptionMenu.js" publishTime="07/01/2013 16:11:09" />
    <file relUrl="bin/Fabrica.dll" publishTime="08/27/2013 19:58:12" />
    <file relUrl="bin/Fabrica.pdb" publishTime="08/27/2013 19:58:12" />
    <file relUrl="Content/Scripts/FormResposta.js" publishTime="04/23/2013 18:07:37" />
    <file relUrl="Content/css/smoothness/images/ui-bg_highlight-soft_75_cccccc_1x100.png" publishTime="03/25/2013 09:53:44" />
    <file relUrl="Content/imgs/eye_32x24.png" publishTime="03/20/2012 20:20:34" />
    <file relUrl="Content/css/smoothness/images/ui-icons_cd0a0a_256x240.png" publishTime="03/25/2013 09:53:44" />
    <file relUrl="Views/PessoaManager/Index.cshtml" publishTime="06/21/2013 11:50:21" />
    <file relUrl="Content/css/FormResposta.css" publishTime="07/24/2013 20:37:08" />
    <file relUrl="Views/Usuario/Detalhes.cshtml" publishTime="05/03/2012 12:27:28" />
    <file relUrl="Content/css/smoothness/images/ui-icons_222222_256x240.png" publishTime="03/25/2013 09:53:44" />
    <file relUrl="Views/MunicipioManager/Index.cshtml" publishTime="06/04/2013 17:59:46" />
    <file relUrl="Content/css/smoothness/images/ui-icons_2e83ff_256x240.png" publishTime="03/25/2013 09:53:44" />
    <file relUrl="Views/EscolaridadeManager/CreateAndUpdate.cshtml" publishTime="06/04/2013 12:19:09" />
    <file relUrl="bin/Ninject.dll" publishTime="04/09/2013 11:57:32" />
    <file relUrl="Content/Scripts/OAT/animation.js" publishTime="03/25/2013 09:53:44" />
    <file relUrl="Content/Scripts/ValidationAndMask.js" publishTime="03/25/2013 09:53:44" />
    <file relUrl="Content/css/ui.jqgrid.css" publishTime="03/25/2013 09:53:44" />
    <file relUrl="Content/Scripts/LogOn.js" publishTime="07/24/2013 22:22:57" />
    <file relUrl="bin/Ninject.Web.Common.xml" publishTime="04/09/2013 11:57:32" />
    <file relUrl="bin/Iesi.Collections.dll" publishTime="03/14/2012 20:43:20" />
    <file relUrl="bin/Microsoft.Web.Infrastructure.dll" publishTime="04/09/2013 11:57:32" />
    <file relUrl="Content/css/GMapsSlider.css" publishTime="04/27/2013 00:40:52" />
    <file relUrl="Content/imgs/barra_top.png" publishTime="04/21/2013 11:57:50" />
    <file relUrl="bin/Ninject.Web.Common.pdb" publishTime="04/09/2013 11:57:32" />
    <file relUrl="bin/ViewWebMvc.dll" publishTime="08/28/2013 16:36:29" />
    <file relUrl="Content/Scripts/CrudMenu.js" publishTime="06/25/2013 09:38:08" />
    <file relUrl="Views/Admin/Index.cshtml" publishTime="08/02/2012 18:49:46" />
    <file relUrl="Content/css/adminIndex.css" publishTime="05/02/2013 15:58:41" />
    <file relUrl="Views/MunicipioManager/CreateAndUpdate.cshtml" publishTime="06/25/2013 10:23:02" />
    <file relUrl="Views/EstadoManager/Index.cshtml" publishTime="06/04/2013 17:51:32" />
    <file relUrl="bin/FabricaNhibernate.pdb" publishTime="08/28/2013 16:36:25" />
    <file relUrl="Content/imgs/ico_busca.png" publishTime="03/25/2013 09:53:44" />
    <file relUrl="bin/ViewWebMvc.pdb" publishTime="08/28/2013 16:36:29" />
    <file relUrl="Views/Home/ResetPassword.cshtml" publishTime="04/27/2013 00:40:52" />
    <file relUrl="packages.config" publishTime="04/09/2013 11:57:42" />
    <file relUrl="Content/imgs/alt_32x32.png" publishTime="03/20/2012 20:23:22" />
    <file relUrl="bin/FluentNHibernate.dll" publishTime="03/14/2012 20:43:24" />
    <file relUrl="bin/Core.pdb" publishTime="08/28/2013 16:36:23" />
    <file relUrl="Content/css/facebookstyle.css" publishTime="05/26/2013 20:38:16" />
    <file relUrl="bin/Persistencia.pdb" publishTime="08/28/2013 16:36:26" />
    <file relUrl="Content/Scripts/OAT/close.png" publishTime="03/25/2013 09:53:44" />
    <file relUrl="Content/imgs/bar-top-content.png" publishTime="06/20/2013 18:13:59" />
    <file relUrl="Views/EstadoManager/CreateAndUpdate.cshtml" publishTime="06/04/2013 17:00:33" />
    <file relUrl="bin/FluentNHibernate.pdb" publishTime="03/14/2012 20:43:24" />
    <file relUrl="bin/Core.dll" publishTime="08/28/2013 16:36:23" />
    <file relUrl="Content/css/smoothness/jquery-ui-1.8.13.custom.css" publishTime="03/25/2013 09:53:44" />
    <file relUrl="bin/Persistencia.dll" publishTime="08/28/2013 16:36:26" />
    <file relUrl="Content/Scripts/ajaxUpdate.js" publishTime="07/24/2013 22:32:15" />
    <file relUrl="Content/Scripts/OAT/bootstrap.js" publishTime="03/25/2013 09:53:44" />
    <file relUrl="Views/EnderecoManager/CreateAndUpdate.cshtml" publishTime="05/28/2013 09:56:11" />
    <file relUrl="Content/Scripts/jquery.ui.datepicker-pt-BR.js" publishTime="03/25/2013 09:53:44" />
    <file relUrl="Views/Home/LogOn.cshtml" publishTime="06/25/2013 20:18:45" />
    <file relUrl="Content/css/smoothness/images/ui-bg_flat_75_ffffff_40x100.png" publishTime="03/25/2013 09:53:44" />
    <file relUrl="Views/Shared/_LogOnPartial.cshtml" publishTime="04/27/2013 00:40:52" />
    <file relUrl="Content/Scripts/jquery.history.js" publishTime="03/25/2013 09:53:44" />
    <file relUrl="Content/Scripts/jquery-1.6.1.js" publishTime="03/25/2013 09:53:44" />
    <file relUrl="Content/imgs/footer_bg.png" publishTime="06/20/2013 11:35:07" />
    <file relUrl="Content/css/formStyle.css" publishTime="03/25/2013 09:53:44" />
    <file relUrl="Content/Scripts/OAT/instant.js" publishTime="03/25/2013 09:53:44" />
    <file relUrl="Content/css/estilo.css" publishTime="07/31/2013 22:45:50" />
    <file relUrl="Views/Usuario/IndexSelect.cshtml" publishTime="08/02/2012 18:49:46" />
    <file relUrl="bin/WebActivator.dll" publishTime="04/09/2013 11:57:32" />
    <file relUrl="bin/Negocio.dll" publishTime="08/28/2013 16:36:27" />
    <file relUrl="Content/imgs/logoTransparente.png" publishTime="03/21/2012 23:57:06" />
    <file relUrl="Views/PessoaManager/CreateAndUpdate.cshtml" publishTime="07/01/2013 15:22:46" />
    <file relUrl="Content/imgs/check_32x26.png" publishTime="03/20/2012 20:27:10" />
    <file relUrl="Content/Scripts/grid.locale-pt-br.js" publishTime="03/25/2013 09:53:44" />
    <file relUrl="Views/Web.config" publishTime="03/14/2012 20:42:52" />
    <file relUrl="bin/AutoCompleteModel.dll" publishTime="08/28/2013 16:36:25" />
    <file relUrl="Views/Home/Overview.cshtml" publishTime="07/24/2013 22:29:57" />
    <file relUrl="Content/css/smoothness/images/ui-bg_inset-soft_75_e6e6e6_1x100.png" publishTime="03/25/2013 09:53:44" />
    <file relUrl="Content/css/smoothness/images/ui-icons_454545_256x240.png" publishTime="03/25/2013 09:53:44" />
    <file relUrl="Content/Scripts/jquery.table2csv.0.1.1.min.js" publishTime="03/25/2013 09:53:44" />
    <file relUrl="bin/AutoCompleteModel.pdb" publishTime="08/28/2013 16:36:25" />
    <file relUrl="bin/Negocio.pdb" publishTime="08/28/2013 16:36:27" />
    <file relUrl="Content/css/smoothness/images/ui-icons_888888_256x240.png" publishTime="03/25/2013 09:53:44" />
    <file relUrl="Content/css/adminCreate.css" publishTime="08/04/2012 15:33:28" />
    <file relUrl="Content/css/admin.css" publishTime="08/08/2012 20:27:32" />
    <file relUrl="LICENSE.txt" publishTime="09/07/2012 20:30:54" />
    <file relUrl="Views/NivelEscolaridadeManager/Index.cshtml" publishTime="06/04/2013 09:27:20" />
    <file relUrl="Content/Scripts/PivotTable.js" publishTime="03/25/2013 09:53:44" />
    <file relUrl="Content/imgs/faces-index.png" publishTime="06/20/2013 11:33:36" />
    <file relUrl="Content/Scripts/jquery.fcbkcomplete.js" publishTime="05/27/2013 09:57:26" />
    <file relUrl="Content/css/smoothness/images/ui-bg_inset-soft_75_a6d0ba_1x100.png" publishTime="03/25/2013 09:53:44" />
    <file relUrl="bin/Ninject.Web.Common.dll" publishTime="04/09/2013 11:57:32" />
    <file relUrl="Content/imgs/btnavancar.png" publishTime="06/27/2013 11:45:22" />
    <file relUrl="Content/Scripts/OAT/loader.js" publishTime="04/06/2013 17:32:56" />
    <file relUrl="Content/css/adminDetalhes.css" publishTime="08/04/2012 15:33:28" />
    <file relUrl="Content/imgs/add_32x32.png" publishTime="03/20/2012 20:29:12" />
    <file relUrl="Views/Resposta/FormResposta.cshtml" publishTime="08/13/2013 15:31:25" />
    <file relUrl="Content/Scripts/OAT/statistics.js" publishTime="03/25/2013 09:53:44" />
    <file relUrl="Content/css/smoothness/images/ui-bg_flat_0_aaaaaa_40x100.png" publishTime="03/25/2013 09:53:44" />
    <file relUrl="Content/imgs/ajax-loader.gif" publishTime="03/25/2013 09:53:44" />
    <file relUrl="Views/Home/ExpiredPage.cshtml" publishTime="03/25/2013 09:53:46" />
    <file relUrl="Views/Usuario/Create.cshtml" publishTime="08/02/2012 18:49:46" />
    <file relUrl="Views/ReportManager/Index.cshtml" publishTime="08/14/2013 10:22:51" />
    <file relUrl="Views/Shared/_Admin.cshtml" publishTime="04/27/2013 00:40:52" />
    <file relUrl="Views/Home/Index.cshtml" publishTime="08/13/2013 10:31:58" />
    <file relUrl="Views/EnderecoManager/Index.cshtml" publishTime="05/28/2013 11:47:38" />
    <file relUrl="Views/Shared/Error.cshtml" publishTime="03/25/2013 09:53:46" />
    <file relUrl="Content/imgs/background.png" publishTime="04/04/2013 22:40:28" />
    <file relUrl="bin/NHibernate.xml" publishTime="03/14/2012 20:43:18" />
    <file relUrl="bin/Modelo.dll" publishTime="08/28/2013 16:36:20" />
    <file relUrl="Content/css/smoothness/images/ui-bg_glass_95_fef1ec_1x400.png" publishTime="03/25/2013 09:53:44" />
  </publishProfile>
</publishData>